<?xml version="1.0" encoding="UTF-8" standalone="no"?>

<beans xmlns="http://www.springframework.org/schema/beans"
	xmlns:xsi="http://www.w3.org/2001/XMLSchema-instance"
	xsi:schemaLocation="http://www.springframework.org/schema/beans http://www.springframework.org/schema/beans/spring-beans-4.3.xsd">

	<!-- Export -->
	<bean id="forms-spreadsheetexport.openDocumentExport"
		class="fr.paris.lutece.plugins.forms.modules.spreadsheetexport.OpenDocumentExport">
		<constructor-arg type="java.lang.String" index="0"
			value="forms-spreadsheetexport.openDocumentExport" />
		<constructor-arg type="java.lang.String" index="1"
			value="module.forms.spreadsheetexport.openDocumentExport.name" />
		<constructor-arg type="java.lang.String" index="2"
			value="module.forms.spreadsheetexport.openDocumentExport.description" />
	</bean>
	<bean id="forms-spreadsheetexport.excelExport"
		class="fr.paris.lutece.plugins.forms.modules.spreadsheetexport.ExcelExport">
		<constructor-arg type="java.lang.String" index="0"
			value="forms-spreadsheetexport.excelExport" />
		<constructor-arg type="java.lang.String" index="1"
			value="module.forms.spreadsheetexport.excelExport.name" />
		<constructor-arg type="java.lang.String" index="2"
			value="module.forms.spreadsheetexport.excelExport.description" />
	</bean>

</beans>